{
  "node": {
    "40530cc2e80ecf78c2c8ac39132a5a1895915f7d60": {
      "workers": {
        "app/[locale]/contacts/page": {
          "moduleId": 6456,
          "async": false,
          "exportedName": "sendTelegramMessage",
          "filename": "src/app/actions/sendTelegramMessage.ts"
        }
      },
      "layer": {
        "app/[locale]/contacts/page": "action-browser"
      },
      "filename": "src/app/actions/sendTelegramMessage.ts",
      "exportedName": "sendTelegramMessage"
    }
  },
  "edge": {},
  "encryptionKey": "0Td/3m52EWTeg4yxg1zoW+mEUvwXfNfeYERdQ+NbLFw="
}